langchain_google_datastore/__init__.py
langchain_google_datastore/chat_message_history.py
langchain_google_datastore/common.py
langchain_google_datastore/document_converter.py
langchain_google_datastore/document_loader.py
langchain_google_datastore/py.typed
langchain_google_datastore/version.py
langchain_google_datastore-0.3.1.dist-info/LICENSE
langchain_google_datastore-0.3.1.dist-info/METADATA
langchain_google_datastore-0.3.1.dist-info/WHEEL
langchain_google_datastore-0.3.1.dist-info/top_level.txt
langchain_google_datastore-0.3.1.dist-info/RECORD
