Metadata-Version: 2.1
Name: langchain-google-datastore
Version: 0.3.1
Summary: LangChain integrations for Google Cloud Datastore
Author-email: Google LLC <googleapis-packages@google.com>
License: 
Project-URL: Homepage, https://github.com/googleapis/langchain-google-datastore-python
Project-URL: Repository, https://github.com/googleapis/langchain-google-datastore-python.git
Project-URL: Bug Tracker, https://github.com/googleapis/langchain-google-datastore-python/issues
Project-URL: Changelog, https://github.com/googleapis/langchain-google-datastore-python/blob/main/CHANGELOG.md
Classifier: Intended Audience :: Developers
Classifier: License :: OSI Approved :: Apache Software License
Classifier: Programming Language :: Python
Classifier: Programming Language :: Python :: 3
Classifier: Programming Language :: Python :: 3.9
Classifier: Programming Language :: Python :: 3.10
Classifier: Programming Language :: Python :: 3.11
Classifier: Programming Language :: Python :: 3.12
Requires-Python: >=3.9
License-File: LICENSE
Requires-Dist: langchain-core <1.0.0,>=0.1.1
Requires-Dist: langchain-community <1.0.0,>=0.0.18
Requires-Dist: google-cloud-datastore <3.0.0,>=2.19.0
Requires-Dist: more-itertools <11.0.0,>=10.2.0
Provides-Extra: test
Requires-Dist: black[jupyter] ==24.10.0 ; extra == 'test'
Requires-Dist: isort ==5.13.2 ; extra == 'test'
Requires-Dist: mypy ==1.13.0 ; extra == 'test'
Requires-Dist: pytest-asyncio ==0.24.0 ; extra == 'test'
Requires-Dist: pytest ==8.3.3 ; extra == 'test'
Requires-Dist: pytest-cov ==5.0.0 ; extra == 'test'
